uhaopt/ABC.py
uhaopt/CMAES.py
uhaopt/CS.py
uhaopt/Cost_function.py
uhaopt/DE.py
uhaopt/SA.py
uhaopt/SPSO2011.py
uhaopt/__init__.py
uhaopt/util.py
uhaopt-2.0.0.dist-info/METADATA
uhaopt-2.0.0.dist-info/WHEEL
uhaopt-2.0.0.dist-info/top_level.txt
uhaopt-2.0.0.dist-info/RECORD
