Metadata-Version: 2.1
Name: uhaopt
Version: 2.0.0
Summary: Metaheuristic optimization package
Home-page: UNKNOWN
Author: Hojjat Rakhshani
Author-email: hojjat.rakhshani@uha.fr
License: UNKNOWN
Platform: UNKNOWN
Classifier: Programming Language :: Python :: 3
Classifier: License :: OSI Approved :: MIT License
Classifier: Operating System :: OS Independent
Requires-Python: >=3.0
